pysqlcipher3/__init__.py
pysqlcipher3/_sqlite3.cpython-36m-x86_64-linux-gnu.so
pysqlcipher3/dbapi2.py
pysqlcipher3/dump.py
pysqlcipher3/test/__init__.py
pysqlcipher3/test/python3/__init__.py
pysqlcipher3/test/python3/dbapi.py
pysqlcipher3/test/python3/dump.py
pysqlcipher3/test/python3/factory.py
pysqlcipher3/test/python3/hooks.py
pysqlcipher3/test/python3/regression.py
pysqlcipher3/test/python3/sqlcipher.py
pysqlcipher3/test/python3/transactions.py
pysqlcipher3/test/python3/types.py
pysqlcipher3/test/python3/userfunctions.py
pysqlcipher3_binary-1.0.4.0.dist-info/LICENSE
pysqlcipher3_binary-1.0.4.0.dist-info/METADATA
pysqlcipher3_binary-1.0.4.0.dist-info/WHEEL
pysqlcipher3_binary-1.0.4.0.dist-info/top_level.txt
pysqlcipher3_binary-1.0.4.0.dist-info/RECORD
