Metadata-Version: 1.1
Name: pysqlcipher3-binary
Version: 1.0.4.0
Summary: DB-API 2.0 interface for SQLCIPHER 3.x
Home-page: https://github.com/rigglemania/pysqlcipher3
Author: David Riggleman
Author-email: davidriggleman@gmail.com
License: zlib/libpng
Platform: ALL
Classifier: Development Status :: 4 - Beta
Classifier: Intended Audience :: Developers
Classifier: License :: OSI Approved :: zlib/libpng License
Classifier: Operating System :: MacOS :: MacOS X
Classifier: Operating System :: Microsoft :: Windows
Classifier: Operating System :: POSIX
Classifier: Programming Language :: C
Classifier: Programming Language :: Python
Classifier: Topic :: Database :: Database Engines/Servers
Classifier: Topic :: Software Development :: Libraries :: Python Modules
